[{"party":"Tamilaga Vettri Kazhagam","short":"TVK","color":"#F59E0B","seats_won":107,"seats_2nd":75,"seats_3rd":51,"seats_4th":0,"total_votes":17226030,"vote_pct":34.92},{"party":"Dravida Munnetra Kazhagam","short":"DMK","color":"#F43F5E","seats_won":60,"seats_2nd":79,"seats_3rd":37,"seats_4th":0,"total_votes":11928996,"vote_pct":24.19},{"party":"All India Anna Dravida Munnetra Kazhagam","short":"AIADMK","color":"#22C55E","seats_won":47,"seats_2nd":44,"seats_3rd":81,"seats_4th":0,"total_votes":10462146,"vote_pct":21.21},{"party":"Indian National Congress","short":"INC","color":"#0EA5E9","seats_won":5,"seats_2nd":11,"seats_3rd":12,"seats_4th":0,"total_votes":1661312,"vote_pct":3.37},{"party":"Pattali Makkal Katchi","short":"PMK","color":"#A855F7","seats_won":4,"seats_2nd":5,"seats_3rd":9,"seats_4th":0,"total_votes":1070745,"vote_pct":2.17},{"party":"Viduthalai Chiruthaigal Katchi","short":"VCK","color":"#06B6D4","seats_won":2,"seats_2nd":4,"seats_3rd":2,"seats_4th":0,"total_votes":540056,"vote_pct":1.09},{"party":"Communist Party of India","short":"CPI","color":"#EC4899","seats_won":2,"seats_2nd":1,"seats_3rd":2,"seats_4th":0,"total_votes":326488,"vote_pct":0.66},{"party":"Communist Party of India (Marxist)","short":"CPI(M)","color":"#6366F1","seats_won":2,"seats_2nd":1,"seats_3rd":2,"seats_4th":0,"total_votes":293817,"vote_pct":0.6},{"party":"Indian Union Muslim League","short":"IUML","color":"#38BDF8","seats_won":2,"seats_2nd":0,"seats_3rd":0,"seats_4th":0,"total_votes":142465,"vote_pct":0.29},{"party":"Bharatiya Janata Party","short":"BJP","color":"#EA580C","seats_won":1,"seats_2nd":8,"seats_3rd":24,"seats_4th":0,"total_votes":1466979,"vote_pct":2.97},{"party":"Desiya Murpokku Dravida Kazhagam","short":"DMDK","color":"#A3E635","seats_won":1,"seats_2nd":4,"seats_3rd":5,"seats_4th":0,"total_votes":589500,"vote_pct":1.2},{"party":"Amma Makkal Munnettra Kazagam","short":"AMMK","color":"#2DD4BF","seats_won":1,"seats_2nd":1,"seats_3rd":9,"seats_4th":0,"total_votes":425345,"vote_pct":0.86},{"party":"Naam Tamilar Katchi","short":"NTK","color":"#8B5CF6","seats_won":0,"seats_2nd":0,"seats_3rd":0,"seats_4th":227,"total_votes":1972520,"vote_pct":4.0},{"party":"Independent","short":"IND","color":"#94A3B8","seats_won":0,"seats_2nd":1,"seats_3rd":0,"seats_4th":1,"total_votes":524740,"vote_pct":1.06},{"party":"None of the Above","short":"NOTA","color":"#64748B","seats_won":0,"seats_2nd":0,"seats_3rd":0,"seats_4th":0,"total_votes":199800,"vote_pct":0.41},{"party":"All India Puratchi Thalaivar Makkal Munnettra Kazhagam","short":"All India ","color":"#94A3B8","seats_won":0,"seats_2nd":0,"seats_3rd":0,"seats_4th":3,"total_votes":133473,"vote_pct":0.27},{"party":"Puthiya Tamilagam","short":"Puthiya Ta","color":"#94A3B8","seats_won":0,"seats_2nd":0,"seats_3rd":0,"seats_4th":0,"total_votes":93652,"vote_pct":0.19},{"party":"Tamizhaga Vaazhvurimai Katchi","short":"Tamizhaga ","color":"#94A3B8","seats_won":0,"seats_2nd":0,"seats_3rd":0,"seats_4th":2,"total_votes":74809,"vote_pct":0.15},{"party":"Bahujan Samaj Party","short":"Bahujan Sa","color":"#94A3B8","seats_won":0,"seats_2nd":0,"seats_3rd":0,"seats_4th":0,"total_votes":53369,"vote_pct":0.11},{"party":"Aanaithinthiya Jananayaka Pathukappu Kazhagam","short":"Aanaithint","color":"#94A3B8","seats_won":0,"seats_2nd":0,"seats_3rd":0,"seats_4th":1,"total_votes":22964,"vote_pct":0.05},{"party":"Republican Party of India (Athawale)","short":"Republican","color":"#94A3B8","seats_won":0,"seats_2nd":0,"seats_3rd":0,"seats_4th":0,"total_votes":11047,"vote_pct":0.02},{"party":"Naadaalum Makkal Katchi","short":"Naadaalum ","color":"#94A3B8","seats_won":0,"seats_2nd":0,"seats_3rd":0,"seats_4th":0,"total_votes":9715,"vote_pct":0.02},{"party":"Veerath Thiyagi Viswanathadoss Thozhilalarkal Katchi","short":"Veerath Th","color":"#94A3B8","seats_won":0,"seats_2nd":0,"seats_3rd":0,"seats_4th":0,"total_votes":5624,"vote_pct":0.01},{"party":"Samaniya Makkal Nala Katchi","short":"Samaniya M","color":"#94A3B8","seats_won":0,"seats_2nd":0,"seats_3rd":0,"seats_4th":0,"total_votes":5144,"vote_pct":0.01},{"party":"Anti Corruption Dynamic Party","short":"Anti Corru","color":"#94A3B8","seats_won":0,"seats_2nd":0,"seats_3rd":0,"seats_4th":0,"total_votes":4558,"vote_pct":0.01},{"party":"Naam Indiar Party","short":"Naam India","color":"#94A3B8","seats_won":0,"seats_2nd":0,"seats_3rd":0,"seats_4th":0,"total_votes":4474,"vote_pct":0.01},{"party":"All India Forward Bloc","short":"All India ","color":"#94A3B8","seats_won":0,"seats_2nd":0,"seats_3rd":0,"seats_4th":0,"total_votes":4455,"vote_pct":0.01},{"party":"Party for the Rights of Other backward Classes","short":"Party for ","color":"#94A3B8","seats_won":0,"seats_2nd":0,"seats_3rd":0,"seats_4th":0,"total_votes":4101,"vote_pct":0.01},{"party":"Thamizhaka Padaippalar Makkal Katchi","short":"Thamizhaka","color":"#94A3B8","seats_won":0,"seats_2nd":0,"seats_3rd":0,"seats_4th":0,"total_votes":4020,"vote_pct":0.01},{"party":"Communist Party of India (Marxist-Leninist) (Liberation)","short":"Communist ","color":"#94A3B8","seats_won":0,"seats_2nd":0,"seats_3rd":0,"seats_4th":0,"total_votes":3983,"vote_pct":0.01},{"party":"Vishwa Tamil Kazhagam","short":"Vishwa Tam","color":"#94A3B8","seats_won":0,"seats_2nd":0,"seats_3rd":0,"seats_4th":0,"total_votes":3576,"vote_pct":0.01},{"party":"Ganasangam Party of India","short":"Ganasangam","color":"#94A3B8","seats_won":0,"seats_2nd":0,"seats_3rd":0,"seats_4th":0,"total_votes":3235,"vote_pct":0.01},{"party":"Anna Puratchi Thalaivar Amma Dravida Munnetra Kazhagam","short":"Anna Purat","color":"#94A3B8","seats_won":0,"seats_2nd":0,"seats_3rd":0,"seats_4th":0,"total_votes":3034,"vote_pct":0.01},{"party":"Puthiya Makkal Tamil Desam Katchi","short":"Puthiya Ma","color":"#94A3B8","seats_won":0,"seats_2nd":0,"seats_3rd":0,"seats_4th":0,"total_votes":2651,"vote_pct":0.01},{"party":"Thakkam Katchi","short":"Thakkam Ka","color":"#94A3B8","seats_won":0,"seats_2nd":0,"seats_3rd":0,"seats_4th":0,"total_votes":2416,"vote_pct":0.0},{"party":"Desiya Makkal Sakthi Katchi","short":"Desiya Mak","color":"#94A3B8","seats_won":0,"seats_2nd":0,"seats_3rd":0,"seats_4th":0,"total_votes":2279,"vote_pct":0.0},{"party":"Indhu Dravida Makkal Katchi","short":"Indhu Drav","color":"#94A3B8","seats_won":0,"seats_2nd":0,"seats_3rd":0,"seats_4th":0,"total_votes":2112,"vote_pct":0.0},{"party":"Tamilar Makkal Katchi","short":"Tamilar Ma","color":"#94A3B8","seats_won":0,"seats_2nd":0,"seats_3rd":0,"seats_4th":0,"total_votes":2056,"vote_pct":0.0},{"party":"Rashtriya Samaj Dal (R)","short":"Rashtriya ","color":"#94A3B8","seats_won":0,"seats_2nd":0,"seats_3rd":0,"seats_4th":0,"total_votes":1760,"vote_pct":0.0},{"party":"Republican Party of India","short":"Republican","color":"#94A3B8","seats_won":0,"seats_2nd":0,"seats_3rd":0,"seats_4th":0,"total_votes":1692,"vote_pct":0.0},{"party":"Tamilaga Makkal Nala Katchi","short":"Tamilaga M","color":"#94A3B8","seats_won":0,"seats_2nd":0,"seats_3rd":0,"seats_4th":0,"total_votes":1555,"vote_pct":0.0},{"party":"Nam Naadu Nam Makkal Nam Ethirkaalam Katchi","short":"Nam Naadu ","color":"#94A3B8","seats_won":0,"seats_2nd":0,"seats_3rd":0,"seats_4th":0,"total_votes":1466,"vote_pct":0.0},{"party":"Anaithinthiya Anna Dravida Makkal Seyal katchi","short":"Anaithinth","color":"#94A3B8","seats_won":0,"seats_2nd":0,"seats_3rd":0,"seats_4th":0,"total_votes":1462,"vote_pct":0.0},{"party":"All India Jananayaka Makkal Kazhagam","short":"All India ","color":"#94A3B8","seats_won":0,"seats_2nd":0,"seats_3rd":0,"seats_4th":0,"total_votes":1415,"vote_pct":0.0},{"party":"All India Youth Development Party","short":"All India ","color":"#94A3B8","seats_won":0,"seats_2nd":0,"seats_3rd":0,"seats_4th":0,"total_votes":1203,"vote_pct":0.0},{"party":"Anna Makkal Katchi","short":"Anna Makka","color":"#94A3B8","seats_won":0,"seats_2nd":0,"seats_3rd":0,"seats_4th":0,"total_votes":1197,"vote_pct":0.0},{"party":"Thamizh Desiya Munnetra Kazhagam","short":"Thamizh De","color":"#94A3B8","seats_won":0,"seats_2nd":0,"seats_3rd":0,"seats_4th":0,"total_votes":1109,"vote_pct":0.0},{"party":"Vanchit Bahujan Aaghadi","short":"Vanchit Ba","color":"#94A3B8","seats_won":0,"seats_2nd":0,"seats_3rd":0,"seats_4th":0,"total_votes":1027,"vote_pct":0.0},{"party":"Makkal Arasial Katchi","short":"Makkal Ara","color":"#94A3B8","seats_won":0,"seats_2nd":0,"seats_3rd":0,"seats_4th":0,"total_votes":1008,"vote_pct":0.0},{"party":"Tamizhaga Murpokku Makkal Katchi","short":"Tamizhaga ","color":"#94A3B8","seats_won":0,"seats_2nd":0,"seats_3rd":0,"seats_4th":0,"total_votes":998,"vote_pct":0.0},{"party":"Ezhuchi Tamilargal Munnetra Kazhagam","short":"Ezhuchi Ta","color":"#94A3B8","seats_won":0,"seats_2nd":0,"seats_3rd":0,"seats_4th":0,"total_votes":802,"vote_pct":0.0},{"party":"Communist Party of India (Marxist-Leninist) Red Star","short":"Communist ","color":"#94A3B8","seats_won":0,"seats_2nd":0,"seats_3rd":0,"seats_4th":0,"total_votes":790,"vote_pct":0.0},{"party":"Bahujan Dravida Party","short":"Bahujan Dr","color":"#94A3B8","seats_won":0,"seats_2nd":0,"seats_3rd":0,"seats_4th":0,"total_votes":780,"vote_pct":0.0},{"party":"Republican Party of India (A)","short":"Republican","color":"#94A3B8","seats_won":0,"seats_2nd":0,"seats_3rd":0,"seats_4th":0,"total_votes":763,"vote_pct":0.0},{"party":"Namadhu Makkal Katchi","short":"Namadhu Ma","color":"#94A3B8","seats_won":0,"seats_2nd":0,"seats_3rd":0,"seats_4th":0,"total_votes":756,"vote_pct":0.0},{"party":"Samata Party","short":"Samata Par","color":"#94A3B8","seats_won":0,"seats_2nd":0,"seats_3rd":0,"seats_4th":0,"total_votes":712,"vote_pct":0.0},{"party":"Tamil Telugu National Party","short":"Tamil Telu","color":"#94A3B8","seats_won":0,"seats_2nd":0,"seats_3rd":0,"seats_4th":0,"total_votes":642,"vote_pct":0.0},{"party":"Socialist Unity Centre Of India (COMMUNIST)","short":"Socialist ","color":"#94A3B8","seats_won":0,"seats_2nd":0,"seats_3rd":0,"seats_4th":0,"total_votes":642,"vote_pct":0.0},{"party":"Vada Tamil Nadu Munnetra Katchi","short":"Vada Tamil","color":"#94A3B8","seats_won":0,"seats_2nd":0,"seats_3rd":0,"seats_4th":0,"total_votes":635,"vote_pct":0.0},{"party":"Nationalist Janshakti Party","short":"Nationalis","color":"#94A3B8","seats_won":0,"seats_2nd":0,"seats_3rd":0,"seats_4th":0,"total_votes":588,"vote_pct":0.0},{"party":"Jebamani Janata","short":"Jebamani J","color":"#94A3B8","seats_won":0,"seats_2nd":0,"seats_3rd":0,"seats_4th":0,"total_votes":586,"vote_pct":0.0},{"party":"All India Uzhavargal Uzhaippalargal Katchi","short":"All India ","color":"#94A3B8","seats_won":0,"seats_2nd":0,"seats_3rd":0,"seats_4th":0,"total_votes":578,"vote_pct":0.0},{"party":"Mannin Maithargal Kazhagam","short":"Mannin Mai","color":"#94A3B8","seats_won":0,"seats_2nd":0,"seats_3rd":0,"seats_4th":0,"total_votes":524,"vote_pct":0.0},{"party":"Our Mahathma National Party","short":"Our Mahath","color":"#94A3B8","seats_won":0,"seats_2nd":0,"seats_3rd":0,"seats_4th":0,"total_votes":508,"vote_pct":0.0},{"party":"Thamizh Perarasu Katchi","short":"Thamizh Pe","color":"#94A3B8","seats_won":0,"seats_2nd":0,"seats_3rd":0,"seats_4th":0,"total_votes":505,"vote_pct":0.0},{"party":"Viro Ke Vir Indian Party","short":"Viro Ke Vi","color":"#94A3B8","seats_won":0,"seats_2nd":0,"seats_3rd":0,"seats_4th":0,"total_votes":498,"vote_pct":0.0},{"party":"Dravida Jananayaga Makkal Katchi","short":"Dravida Ja","color":"#94A3B8","seats_won":0,"seats_2nd":0,"seats_3rd":0,"seats_4th":0,"total_votes":486,"vote_pct":0.0},{"party":"New Generation People's Party","short":"New Genera","color":"#94A3B8","seats_won":0,"seats_2nd":0,"seats_3rd":0,"seats_4th":0,"total_votes":476,"vote_pct":0.0},{"party":"Makkal Nalvaazhvuk Katchi","short":"Makkal Nal","color":"#94A3B8","seats_won":0,"seats_2nd":0,"seats_3rd":0,"seats_4th":0,"total_votes":461,"vote_pct":0.0},{"party":"Indian National League","short":"Indian Nat","color":"#94A3B8","seats_won":0,"seats_2nd":0,"seats_3rd":0,"seats_4th":0,"total_votes":457,"vote_pct":0.0},{"party":"Akila Inthiya Makkal Marumalarchi Kazhakam","short":"Akila Inth","color":"#94A3B8","seats_won":0,"seats_2nd":0,"seats_3rd":0,"seats_4th":0,"total_votes":425,"vote_pct":0.0},{"party":"MAKKAL SAKTHI KATCHI","short":"MAKKAL SAK","color":"#94A3B8","seats_won":0,"seats_2nd":0,"seats_3rd":0,"seats_4th":0,"total_votes":424,"vote_pct":0.0},{"party":"Rashtriya Janata Dal","short":"Rashtriya ","color":"#94A3B8","seats_won":0,"seats_2nd":0,"seats_3rd":0,"seats_4th":0,"total_votes":402,"vote_pct":0.0},{"party":"Tamil Nadu Ilangyar Katchi","short":"Tamil Nadu","color":"#94A3B8","seats_won":0,"seats_2nd":0,"seats_3rd":0,"seats_4th":0,"total_votes":355,"vote_pct":0.0},{"party":"Ahimsa Socialist Party","short":"Ahimsa Soc","color":"#94A3B8","seats_won":0,"seats_2nd":0,"seats_3rd":0,"seats_4th":0,"total_votes":321,"vote_pct":0.0},{"party":"Tamil Manila Murpokku Dravida Kazhagam","short":"Tamil Mani","color":"#94A3B8","seats_won":0,"seats_2nd":0,"seats_3rd":0,"seats_4th":0,"total_votes":319,"vote_pct":0.0},{"party":"Democratic National Allegiance","short":"Democratic","color":"#94A3B8","seats_won":0,"seats_2nd":0,"seats_3rd":0,"seats_4th":0,"total_votes":311,"vote_pct":0.0},{"party":"Makkal Munnetra Katchi","short":"Makkal Mun","color":"#94A3B8","seats_won":0,"seats_2nd":0,"seats_3rd":0,"seats_4th":0,"total_votes":305,"vote_pct":0.0},{"party":"Anna MGR Dravida Makkal Kalgam","short":"Anna MGR D","color":"#94A3B8","seats_won":0,"seats_2nd":0,"seats_3rd":0,"seats_4th":0,"total_votes":295,"vote_pct":0.0},{"party":"Parivartan Rajniti Party","short":"Parivartan","color":"#94A3B8","seats_won":0,"seats_2nd":0,"seats_3rd":0,"seats_4th":0,"total_votes":291,"vote_pct":0.0},{"party":"Makkal Nala Kazhagam","short":"Makkal Nal","color":"#94A3B8","seats_won":0,"seats_2nd":0,"seats_3rd":0,"seats_4th":0,"total_votes":285,"vote_pct":0.0},{"party":"Ahila India Dhayaga Makkal Munnetra Katchi","short":"Ahila Indi","color":"#94A3B8","seats_won":0,"seats_2nd":0,"seats_3rd":0,"seats_4th":0,"total_votes":283,"vote_pct":0.0},{"party":"Desa Makkal Munnetrak Kazhagam","short":"Desa Makka","color":"#94A3B8","seats_won":0,"seats_2nd":0,"seats_3rd":0,"seats_4th":0,"total_votes":278,"vote_pct":0.0},{"party":"National Maha Sabha Party","short":"National M","color":"#94A3B8","seats_won":0,"seats_2nd":0,"seats_3rd":0,"seats_4th":0,"total_votes":278,"vote_pct":0.0},{"party":"Bharat Jan Chikitsa Party","short":"Bharat Jan","color":"#94A3B8","seats_won":0,"seats_2nd":0,"seats_3rd":0,"seats_4th":0,"total_votes":276,"vote_pct":0.0},{"party":"Periyar Ambedkar Munnetra Kazhagam (PAMK)","short":"Periyar Am","color":"#94A3B8","seats_won":0,"seats_2nd":0,"seats_3rd":0,"seats_4th":0,"total_votes":274,"vote_pct":0.0},{"party":"Kamarajar Deseeya Congress","short":"Kamarajar ","color":"#94A3B8","seats_won":0,"seats_2nd":0,"seats_3rd":0,"seats_4th":0,"total_votes":244,"vote_pct":0.0},{"party":"Vidial Valarchi Perani","short":"Vidial Val","color":"#94A3B8","seats_won":0,"seats_2nd":0,"seats_3rd":0,"seats_4th":0,"total_votes":235,"vote_pct":0.0},{"party":"India Suyarajya Party","short":"India Suya","color":"#94A3B8","seats_won":0,"seats_2nd":0,"seats_3rd":0,"seats_4th":0,"total_votes":224,"vote_pct":0.0},{"party":"Anaithindia Samudaya Munnetra Kazhagam","short":"Anaithindi","color":"#94A3B8","seats_won":0,"seats_2nd":0,"seats_3rd":0,"seats_4th":0,"total_votes":224,"vote_pct":0.0},{"party":"Viduthalai Kalam Katchi","short":"Viduthalai","color":"#94A3B8","seats_won":0,"seats_2nd":0,"seats_3rd":0,"seats_4th":0,"total_votes":211,"vote_pct":0.0},{"party":"Namathu Kongu Munnetra Kalagam","short":"Namathu Ko","color":"#94A3B8","seats_won":0,"seats_2nd":0,"seats_3rd":0,"seats_4th":0,"total_votes":200,"vote_pct":0.0},{"party":"Thamizhaga Munnetra Congress","short":"Thamizhaga","color":"#94A3B8","seats_won":0,"seats_2nd":0,"seats_3rd":0,"seats_4th":0,"total_votes":186,"vote_pct":0.0},{"party":"Bharatha Makkal Katchi","short":"Bharatha M","color":"#94A3B8","seats_won":0,"seats_2nd":0,"seats_3rd":0,"seats_4th":0,"total_votes":183,"vote_pct":0.0},{"party":"All India Majlis-E-Inquilab-E-Millat","short":"All India ","color":"#94A3B8","seats_won":0,"seats_2nd":0,"seats_3rd":0,"seats_4th":0,"total_votes":168,"vote_pct":0.0},{"party":"Makkal Sananayaga Kudiyarasu Katchi","short":"Makkal San","color":"#94A3B8","seats_won":0,"seats_2nd":0,"seats_3rd":0,"seats_4th":0,"total_votes":149,"vote_pct":0.0},{"party":"MGR Makkal Katchi","short":"MGR Makkal","color":"#94A3B8","seats_won":0,"seats_2nd":0,"seats_3rd":0,"seats_4th":0,"total_votes":131,"vote_pct":0.0},{"party":"Proutist Sarva Samaj","short":"Proutist S","color":"#94A3B8","seats_won":0,"seats_2nd":0,"seats_3rd":0,"seats_4th":0,"total_votes":130,"vote_pct":0.0},{"party":"Thamizhaga Dravidar Katchi","short":"Thamizhaga","color":"#94A3B8","seats_won":0,"seats_2nd":0,"seats_3rd":0,"seats_4th":0,"total_votes":120,"vote_pct":0.0},{"party":"Makkal Murasu Katchi","short":"Makkal Mur","color":"#94A3B8","seats_won":0,"seats_2nd":0,"seats_3rd":0,"seats_4th":0,"total_votes":94,"vote_pct":0.0},{"party":"Indian Christian Front","short":"Indian Chr","color":"#94A3B8","seats_won":0,"seats_2nd":0,"seats_3rd":0,"seats_4th":0,"total_votes":85,"vote_pct":0.0},{"party":"Indhia Kudiarasu Katchi","short":"Indhia Kud","color":"#94A3B8","seats_won":0,"seats_2nd":0,"seats_3rd":0,"seats_4th":0,"total_votes":82,"vote_pct":0.0},{"party":"Tamilnadu Mahatma Gandhi Makkal Katchi","short":"Tamilnadu ","color":"#94A3B8","seats_won":0,"seats_2nd":0,"seats_3rd":0,"seats_4th":0,"total_votes":71,"vote_pct":0.0},{"party":"ALL PENSIONER'S PARTY","short":"ALL PENSIO","color":"#94A3B8","seats_won":0,"seats_2nd":0,"seats_3rd":0,"seats_4th":0,"total_votes":55,"vote_pct":0.0},{"party":"Makkalatchi Katchi","short":"Makkalatch","color":"#94A3B8","seats_won":0,"seats_2nd":0,"seats_3rd":0,"seats_4th":0,"total_votes":46,"vote_pct":0.0}]